source_avni/__init__.py
source_avni/components.py
source_avni/manifest.yaml
source_avni/run.py
source_avni/schemas/encounters.json
source_avni/schemas/program_encounters.json
source_avni/schemas/program_enrolments.json
source_avni/schemas/subjects.json
source_avni/source.py
airbyte_source_avni-0.1.1.dist-info/METADATA
airbyte_source_avni-0.1.1.dist-info/WHEEL
airbyte_source_avni-0.1.1.dist-info/entry_points.txt
airbyte_source_avni-0.1.1.dist-info/RECORD
